{
  "menus": [
    {
      "id": "0.1",
      "level": 0,
      "menu": "Home",
      "parent": "",
      "description": "Welcome to Kendal the home of Olrig Bank"
    },
    {
      "id": "0.2",
      "level": 1,
      "menu": "Whats On",
      "parent": "Home",
      "description": "Links to sites that will keep you abreast about what is happening"
    },
    {
      "id": "0.3",
      "level": 1,
      "menu": "Outdoor Pursuits",
      "parent": "Home",
      "description": "Local delights"
    },
    {
      "id": "0.4",
      "level": 2,
      "menu": "Close to home",
      "parent": "Outdoor Pursuits",
      "description": "Exploring in the Great Outdoors"
    },
    {
      "id": "0.5",
      "level": 2,
      "menu": "Further afield",
      "parent": "Outdoor Pursuits",
      "description": "Exploring in the Great Outdoors"
    },
    {
      "id": "0.6",
      "level": 2,
      "menu": "Cycling",
      "description": "Range far and wide without the car!",
      "parent": "Outdoor Pursuits"
    },
    {
      "id": "0.7",
      "level": 1,
      "menu": "Local",
      "parent": "Home",
      "description": "Local delights"
    },
    {
      "id": "0.8",
      "level": 2,
      "menu": "Eating Out",
      "parent": "Local",
      "description": "Places we where we love to eat"
    },
    {
      "id": "0.9",
      "level": 2,
      "menu": "Bars",
      "description": "Watering holes for every taste",
      "parent": "Local"
    },
    {
      "id": "0.10",
      "level": 2,
      "menu": "Activities",
      "parent": "Local",
      "description": "A wide variety of local activities"
    },
    {
      "id": "0.11",
      "level": 2,
      "menu": "Exhibitions",
      "description": "All well worth a visit ",
      "parent": "Local"
    },
    {
      "id": "0.12",
      "level": 2,
      "menu": "Shopping",
      "description": "Local Shops with character",
      "parent": "Local"
    },
    {
      "id": "0.13",
      "level": 2,
      "menu": "Music",
      "description": "Live Music Venues",
      "parent": "Local"
    },
    {
      "id": "0.14",
      "level": 2,
      "menu": "Pre-owned",
      "description": "Shops that can be just a delight to wander around",
      "parent": "Local"
    },
    {
      "id": "0.15",
      "level": 3,
      "menu": "Antiques",
      "description": "Hopefully full of objects that all over 100 years old and curated by people with years of experience",
      "parent": "Pre-owned"
    },
    {
      "id": "0.16",
      "level": 3,
      "menu": "Collectables",
      "description": "Collectable is in the eye of the collector!",
      "parent": "Pre-owned"
    },
    {
      "id": "0.17",
      "level": 1,
      "menu": "Festivals",
      "description": "Gatherings that are still come this year",
      "parent": "Home"
    }
  ],
  "offerings": [
    {
      "id": "1.1",
      "image": "whatsonkendal",
      "link": "https://visit-kendal.co.uk/",
      "menu": "Whats On",
      "title": "The Visit Kendal Site",
      "description": "The easiest way to find out what is going on in the town during your stay"
    },
    {
      "id": "1.2",
      "image": "Babaganoush",
      "link": "https://babaganoushkendal.co.uk/",
      "menu": "Eating Out",
      "title": "Baba Ganoush",
      "description": "What a place! When it is open"
    },
    {
      "id": "1.3",
      "image": "kendalpeoplescafe",
      "link": "https://wasteintowellbeing.org.uk/kendal-peoples-cafe/",
      "menu": "Eating Out",
      "title": "Kendal People Cafe",
      "description": "A great place to eat and to see a community in action"
    },
    {
      "id": "1.4",
      "image": "kendalcastle",
      "link": "https://apathtosomewhere.co.uk/2021/04/14/kendal-castle/",
      "menu": "Close to home",
      "title": "Kendal Castle",
      "description": "The first walk to take after you have settled in to Olrig Bank!"
    },
    {
      "id": "1.5",
      "image": "kcw",
      "link": "https://lakelandclimbingcentres.co.uk/centre/kendalwall/",
      "menu": "Activities",
      "title": "Kendal Climbing Wall",
      "description": "Kids climbing the walls? Why not visit the Kendal Climbing Wall!"
    },
    {
      "id": "1.6",
      "menu": "Shopping",
      "title": "Watson & Wollard",
      "description": "A high quality traditional local butcher on the marketplace",
      "link": "https://www.facebook.com/watsonandwoollardbutchers/",
      "image": "watson-wollard"
    },
    {
      "id": "1.7",
      "menu": "Music",
      "title": "Ruskins",
      "description": "Popular town centre bar with regular live music from acoustic jam nights to reggae, folk nights to electronica - with the odd quiz night inbetween - Ruskins is a hidden gem on Kendal high street",
      "link": "https://www.facebook.com/Ruskinskendal",
      "image": "ruskins"
    },
    {
      "id": "1.8",
      "menu": "Festivals",
      "title": "The Kendal Mountain Festival",
      "description": "The Everest of Festivals ",
      "link": "https://www.kendalmountainfestival.com/",
      "image": "mountain"
    },
    {
      "id": "1.9",
      "menu": "Festivals",
      "title": "The Lakes International Comic Art Festival",
      "description": "A fun family festival that has grown and grown over the last 10 years",
      "link": "https://www.facebook.com/LakesInternationalComicArtFestival/",
      "image": "comic-art-featival"
    },
    {
      "id": "1.10",
      "menu": "Music",
      "title": "The Brewery",
      "description": "Attracts great acts",
      "link": "https://www.breweryarts.co.uk/whats-on/live-music/",
      "image": "Brewery-music"
    },
    {
      "id": "1.11",
      "menu": "Music",
      "title": "Kendal Music Feastival",
      "description": "Kendal's Annual music Feastival",
      "link": "https://visit-kendal.co.uk/event/kendal-music-festival-2/",
      "image": "kendal-music-feastival"
    },
    {
      "id": "1.12",
      "menu": "Music",
      "title": "Kendal Jazz club",
      "description": "New to the Brewery",
      "link": "https://www.breweryarts.co.uk/event/jazz-club/",
      "image": "kendal-jazz"
    },
    {
      "id": "1.13",
      "menu": "Shopping",
      "title": "The Staff Of Life",
      "description": "An absolutely lovely bakery",
      "link": "https://www.facebook.com/bakenyinkendal/",
      "image": "staff-of-life"
    },
    {
      "id": "1.14",
      "menu": "Shopping",
      "title": "Kendal Fish & Seafoods",
      "description": "A great fishmonger on Stramongate",
      "link": "https://www.facebook.com/kendalfishltd/",
      "image": "kendalfishandseafoods"
    },
    {
      "id": "1.15",
      "menu": "Collectables",
      "title": "The Nutshell",
      "description": "A gem, Crammed to the rafters with stuff! some of it is very valuable  ",
      "link": "https://www.google.com/maps/place//data=!4m2!3m1!1s0x487c8de746e95feb:0xbb11fc5e10c5b453?sa=X&ved=1t:8290&ictx=111",
      "image": "nutshell"
    },
    {
      "id": "1.16",
      "menu": "Eating Out",
      "title": "The Joshua Tree",
      "description": "Provides a great English Breakfast and wonderful lunches",
      "link": "https://joshuatreebistro.co.uk/",
      "image": "JoshuaTree"
    },
    {
      "id": "1.17",
      "menu": "Antiques",
      "title": "The Old Curiosity Shop",
      "description": "A modern take on The Nutshell?",
      "link": "https://tocshop.co.uk/",
      "image": "tocshop"
    },
    {
      "id": "1.18",
      "menu": "Bars",
      "title": "The Fell",
      "description": "An absolutely cracking bar with atmosphere and games",
      "link": "https://fellbrewery.co.uk/venues/fell-kendal/",
      "image": "thefell"
    },
    {
      "id": "1.19",
      "menu": "Close to home",
      "title": "Serpentine Woods",
      "description": "From Noble's Rest Park it is short upwards walk to the entrance to the woods",
      "link": "https://apathtosomewhere.co.uk/2023/03/21/serpentine-woods-kendal/",
      "image": "serpentine-woods"
    },
    {
      "id": "1.20",
      "menu": "Close to home",
      "title": "Cunswick Scar and Scout Scar",
      "description": "Starting from the Serpentine Woods a 7.25 mile circular route that Wainright described as: a walk above others, a pleasure every step of the way",
      "link": "https://www.wainwrightwalking.co.uk/cunswick-scar-and-scout-scar/",
      "image": "scoutscar"
    },
    {
      "id": "1.21",
      "menu": "Close to home",
      "title": "Craggy Wood",
      "description": "Park in the village of Staverly. Walk past the bowling Green, cross a small stream and walk through a farm. From there you can find a circular route that takes you through these atmospheric woods , ending on a downhill walk though fields of sheep and back to the village",
      "link": "https://www.cumbriawildlifetrust.org.uk/nature-reserves/staveley-woodlands",
      "image": "SraveleyWoodlands"
    },
    {
      "id": "1.22",
      "menu": "Further afield",
      "title": "Gummer's How",
      "description": "An easy walk to a magnificent view over Windermere",
      "link": "http://www.wainwrightroutes.co.uk/gummershow_r1.htm",
      "image": "gummershowe"
    },
    {
      "id": "1.23",
      "menu": "Further afield",
      "title": "Fell Foot Park",
      "description": "Lakeshore park with stunning mountain views, Boathouse cafe, watersports hire and play area",
      "link": "https://www.nationaltrust.org.uk/visit/lake-district/fell-foot",
      "image": "fellfoot"
    },
    {
      "id": "1.24",
      "menu": "Cycling",
      "title": "Cycling around Kendal",
      "description": "courtesy of the Kendal Mountain Festival",
      "link": "https://www.komoot.com/collection/1294854/road-mountain-biking-and-gravel-routes-from-kendal",
      "image": "cyclingKendal"
    },
    {
      "id": "1.25",
      "menu": "Activities",
      "title": "The Albion Social & Snooker Club",
      "description": "Excellent snooker tables. Well-kept real ales at reasonable prices. Free entry for CAMRA members.",
      "link": "https://www.google.com/search?sa=X&sca_esv=43bdce033f74f264&rlz=1C1ONGR_enNL1022NL1022&tbm=lcl&sxsrf=AE3TifOIxWycKq1LfFWpmhgNkhOnw0-AnA:1750343693447&q=The+Albion+Social+%26+Snooker+Club+Reviews&rflfq=1&num=20&stick=H4sIAAAAAAAAAONgkxI2NDY1MzY0MjCyNDW1tLQ0M7a02MDI-IpRIyQjVcExJykzP08hOD85MzFHQU0hOC8_Pzu1SME5pzRJISi1LDO1vHgRK9FKAajp5HFwAAAA&rldimm=1356312029559996398&hl=en-NL&ved=2ahUKEwiWvdSw2v2NAxVx1gIHHaVkNOkQ9fQKegQIVxAF&biw=2560&bih=1313&dpr=1#lkt=LocalPoiReviews",
      "image": "AlbionSnookerHall"
    },
    {
      "id": "1.26",
      "menu": "Festivals",
      "title": "Kendal Walking Festival",
      "description": "This well established festival continues to demonstrate why Kendal makes a superb base for those who enjoy walking. Surrounded by beautiful scenery it offers a wide variety of walking experiences. It is a 5-minute drive into the Lake District National Park and 20 minutes from the Yorkshire Dales. In addition we have Arnside and Silverdale Area of Outstanding Natural Beauty just a few miles south of town.  We really do have it all....mountains, lakes, rivers, valleys and the wide open vistas of Morecambe Bay!!",
      "link": "https://www.kendalwalkingfestival.co.uk/home",
      "image": "kendalwalkingfestival"
    },
    {
      "id": "1.27",
      "menu": "Home",
      "title": "Olrig Bank",
      "description": "A fine place to stay",
      "link": "https://www.airbnb.co.uk/rooms/1291126414271510916?viralityEntryPoint=1&s=76&source_impression_id=p3_1750413104_P3PD8jAtNyPJE9WL",
      "image": "olrigbank"
    },
    {
      "id": "1.28",
      "menu": "Further afield",
      "title": "Ingleborough Cave",
      "description": "A visit could give you a taste for serious caving",
      "link": "https://ingleboroughcave.co.uk/",
      "image": "ingenlboroughcave"
    },
    {
      "id": "1.29",
      "menu": "Bars",
      "title": "Ring O Bells",
      "description": "Historic, quirky and charismatic local pub serving real ales and food homemade by landlady Su. Enjoy a drink in the cosy Bell Ringers Snug. Rumounred to be folk music sessions each Monday evening.",
      "link": "https://www.ringobellskendal.com/",
      "image": "ring-o-bells"
    },
    {
      "id": "1.30",
      "menu": "Exhibitions",
      "title": "Abbot Hall",
      "description": "One of the UK''s leading art galleries. Established in 1962 in a Grade I listed Georgian building on the banks of the River Kent in Kendal, today we are rethinking the gallery as vibrant cultural and community hub. ",
      "link": "https://lakelandarts.org.uk/abbot-hall/",
      "image": "abbothall"
    },
    {
      "id": "1.31",
      "image": "qtm",
      "link": "https://www.quaker-tapestry.co.uk/",
      "menu": "Exhibitions",
      "title": "The Quaker Tapestry",
      "description": "The story of Quakers in 77 embroidered panels"
    },
    {
      "id": "1.32",
      "menu": "Close to home",
      "title": "The Helm",
      "description": "Situated near Oxenholme, just south east of Kendal and although not a very high hill at 185m, it gives beautiful views.",
      "link": "https://www.friendsofthelakedistrict.org.uk/the-helm",
      "image": "thehelm"
    },
    {
      "id": "1.33",
      "menu": "Further afield",
      "title": "Gurnal Dubs Tarn",
      "description": "A beautiful tarn below the minor summit of Ulgraves, not far from the village of Staveley. On the walk in, you are rewarded with superb views across nearby Kendal. Although it is actually an artificial tarn, it still makes for a lovely spot for a wild swim in summer.",
      "link": "https://www.komoot.com/highlight/3590524",
      "image": "GurnalDubsTarn"
    },
    {
      "id": "1.34",
      "menu": "Further afield",
      "title": "Rock Climbing",
      "description": "The Lakes is the ideal place to take a beginners course",
      "link": "https://www.mountain-journeys.co.uk/trad-climbing-course-lake-district/",
      "image": "tradclimbing"
    },
    {
      "id": "1.35",
      "menu": "Close to home",
      "title": "Sizergh Fell Walk",
      "description": "The traditional agricultural estate that surrounds Sizergh offers dramatic views of the Lakeland Fells, the Pennines and Morecambe Bay, as well as a fantastic array of animals, birds, butterflies and wildflowers that vary with the seasons.",
      "link": "https://www.nationaltrust.org.uk/visit/lake-district/sizergh/sizergh-wildlife-walk",
      "image": "SizerghFellwalk"
    },
    {
      "id": "1.36",
      "menu": "Close to home",
      "title": "Park End Moss Wetland",
      "description": "Park End Moss Wetland wWlk at Sizergh was once an area of degraded farmland that has now been transformed into a haven for wildlife. This circular walk takes you through historic parkland and ancient woodlands of the Sizergh estate and on to the wetland area which is popular with a variety of bird species.",
      "link": "https://www.nationaltrust.org.uk/visit/lake-district/sizergh/park-end-moss-wetland-walk-at-sizergh",
      "image": "park-end-moss-wetland-walk-at-sizergh"
    },
    {
      "id": "1.37",
      "menu": "Cycling",
      "title": "The Bay Cycle Way",
      "description": "Kendal to the Arnside, Silverdale, Beetham loop",
      "link": "https://www.waysaroundthebay.org.uk/cycle-morecambe-bay",
      "image": "baycycleway"
    }
  ]
}